<?xml version="1.0" encoding="windows-1252" ?>
<!DOCTYPE ViewObject SYSTEM "jbo_03_01.dtd">
<!---->
<ViewObject
  xmlns="http://xmlns.oracle.com/bc4j"
  Name="supplierContactROVO"
  Version="11.1.1.66.73"
  InheritPersonalization="merge"
  BindingStyle="OracleName"
  CustomQuery="true"
  PageIterMode="Full"
  UseGlueCode="false">
  <DesignTime>
    <Attr Name="_isExpertMode" Value="true"/>
  </DesignTime>
  <Properties>
    <SchemaBasedProperties>
      <LABEL
        ResId="ROVO.supplierContactROVO_LABEL"/>
    </SchemaBasedProperties>
  </Properties>
  <Variable
    Name="BV_Site_ID"
    Kind="viewcriteria"
    Type="java.lang.String"/>
  <Variable
    Name="BV_CONT_ID"
    Kind="viewcriteria"
    Type="java.lang.String"/>
  <Variable
    Name="BV_SUPSITE_ID"
    Kind="where"
    Type="java.lang.String"/>
  <SQLQuery>
    <![CDATA[SELECT 
    XXSTG_VENDOR_CONTACTS.VENDOR_CONTACT_ID VENDOR_CONTACT_ID, 
    XXSTG_VENDOR_CONTACTS.VENDOR_ID VENDOR_ID, 
    XXSTG_VENDOR_CONTACTS.VENDOR_SITE_ID VENDOR_SITE_ID, 
    XXSTG_VENDOR_CONTACTS.FULL_NAME FULL_NAME, 
    XXSTG_VENDOR_CONTACTS.PARTY_NAME PARTY_NAME, 
    XXSTG_VENDOR_CONTACTS.EMAIL_ADDRESS EMAIL_ADDRESS, 
    XXSTG_VENDOR_CONTACTS.PHONE_COUNTRY_CODE PHONE_COUNTRY_CODE, 
    XXSTG_VENDOR_CONTACTS.PHONE_AREA_CODE PHONE_AREA_CODE, 
    XXSTG_VENDOR_CONTACTS.PHONE PHONE, 
    XXSTG_VENDOR_CONTACTS.PHONE_EXTENSION PHONE_EXTENSION, 
    XXSTG_VENDOR_CONTACTS.PHONE_NUMBER PHONE_NUMBER, 
    XXSTG_VENDOR_CONTACTS.MOBILE_COUNTRY_CODE MOBILE_COUNTRY_CODE, 
    XXSTG_VENDOR_CONTACTS.MOBILE_AREA_CODE MOBILE_AREA_CODE, 
    XXSTG_VENDOR_CONTACTS.MOBILE MOBILE, 
    XXSTG_VENDOR_CONTACTS.MOBILE_NUMBER MOBILE_NUMBER, 
    XXSTG_VENDOR_CONTACTS.STATUS STATUS, 
    XXSTG_VENDOR_CONTACTS.INACTIVE_DATE INACTIVE_DATE 
FROM 
    XXSTG_VENDOR_CONTACTS
WHERE 
    XXSTG_VENDOR_CONTACTS.VENDOR_SITE_ID=:BV_SUPSITE_ID]]>
  </SQLQuery>
  <ViewAttribute
    Name="VendorContactId"
    IsUpdateable="false"
    IsPersistent="false"
    IsNotNull="true"
    PrecisionRule="true"
    Type="oracle.jbo.domain.Number"
    ColumnType="NUMBER"
    AliasName="VENDOR_CONTACT_ID"
    Expression="VENDOR_CONTACT_ID"
    SQLType="NUMERIC">
    <DesignTime>
      <Attr Name="_DisplaySize" Value="39"/>
    </DesignTime>
  </ViewAttribute>
  <ViewAttribute
    Name="VendorId"
    IsUpdateable="false"
    IsPersistent="false"
    PrecisionRule="true"
    Type="oracle.jbo.domain.Number"
    ColumnType="NUMBER"
    AliasName="VENDOR_ID"
    Expression="VENDOR_ID"
    SQLType="NUMERIC">
    <DesignTime>
      <Attr Name="_DisplaySize" Value="39"/>
    </DesignTime>
  </ViewAttribute>
  <ViewAttribute
    Name="VendorSiteId"
    IsUpdateable="false"
    IsPersistent="false"
    IsNotNull="true"
    PrecisionRule="true"
    Type="oracle.jbo.domain.Number"
    ColumnType="NUMBER"
    AliasName="VENDOR_SITE_ID"
    Expression="VENDOR_SITE_ID"
    SQLType="NUMERIC">
    <DesignTime>
      <Attr Name="_DisplaySize" Value="39"/>
    </DesignTime>
  </ViewAttribute>
  <ViewAttribute
    Name="FullName"
    IsUpdateable="false"
    IsPersistent="false"
    PrecisionRule="true"
    Precision="2000"
    Type="java.lang.String"
    ColumnType="VARCHAR2"
    AliasName="FULL_NAME"
    Expression="FULL_NAME"
    SQLType="VARCHAR">
    <DesignTime>
      <Attr Name="_DisplaySize" Value="2000"/>
    </DesignTime>
  </ViewAttribute>
  <ViewAttribute
    Name="PartyName"
    IsUpdateable="false"
    IsPersistent="false"
    PrecisionRule="true"
    Precision="2000"
    Type="java.lang.String"
    ColumnType="VARCHAR2"
    AliasName="PARTY_NAME"
    Expression="PARTY_NAME"
    SQLType="VARCHAR">
    <DesignTime>
      <Attr Name="_DisplaySize" Value="2000"/>
    </DesignTime>
  </ViewAttribute>
  <ViewAttribute
    Name="EmailAddress"
    IsUpdateable="false"
    IsPersistent="false"
    PrecisionRule="true"
    Precision="320"
    Type="java.lang.String"
    ColumnType="VARCHAR2"
    AliasName="EMAIL_ADDRESS"
    Expression="EMAIL_ADDRESS"
    SQLType="VARCHAR">
    <DesignTime>
      <Attr Name="_DisplaySize" Value="320"/>
    </DesignTime>
  </ViewAttribute>
  <ViewAttribute
    Name="PhoneCountryCode"
    IsUpdateable="false"
    IsPersistent="false"
    PrecisionRule="true"
    Precision="100"
    Type="java.lang.String"
    ColumnType="VARCHAR2"
    AliasName="PHONE_COUNTRY_CODE"
    Expression="PHONE_COUNTRY_CODE"
    SQLType="VARCHAR">
    <DesignTime>
      <Attr Name="_DisplaySize" Value="100"/>
    </DesignTime>
  </ViewAttribute>
  <ViewAttribute
    Name="PhoneAreaCode"
    IsUpdateable="false"
    IsPersistent="false"
    PrecisionRule="true"
    Precision="100"
    Type="java.lang.String"
    ColumnType="VARCHAR2"
    AliasName="PHONE_AREA_CODE"
    Expression="PHONE_AREA_CODE"
    SQLType="VARCHAR">
    <DesignTime>
      <Attr Name="_DisplaySize" Value="100"/>
    </DesignTime>
  </ViewAttribute>
  <ViewAttribute
    Name="Phone"
    IsUpdateable="false"
    IsPersistent="false"
    PrecisionRule="true"
    Precision="100"
    Type="java.lang.String"
    ColumnType="VARCHAR2"
    AliasName="PHONE"
    Expression="PHONE"
    SQLType="VARCHAR">
    <DesignTime>
      <Attr Name="_DisplaySize" Value="100"/>
    </DesignTime>
  </ViewAttribute>
  <ViewAttribute
    Name="PhoneExtension"
    IsUpdateable="false"
    IsPersistent="false"
    PrecisionRule="true"
    Precision="100"
    Type="java.lang.String"
    ColumnType="VARCHAR2"
    AliasName="PHONE_EXTENSION"
    Expression="PHONE_EXTENSION"
    SQLType="VARCHAR">
    <DesignTime>
      <Attr Name="_DisplaySize" Value="100"/>
    </DesignTime>
  </ViewAttribute>
  <ViewAttribute
    Name="PhoneNumber"
    IsUpdateable="false"
    IsPersistent="false"
    PrecisionRule="true"
    Precision="100"
    Type="java.lang.String"
    ColumnType="VARCHAR2"
    AliasName="PHONE_NUMBER"
    Expression="PHONE_NUMBER"
    SQLType="VARCHAR">
    <DesignTime>
      <Attr Name="_DisplaySize" Value="100"/>
    </DesignTime>
  </ViewAttribute>
  <ViewAttribute
    Name="MobileCountryCode"
    IsUpdateable="false"
    IsPersistent="false"
    PrecisionRule="true"
    Precision="100"
    Type="java.lang.String"
    ColumnType="VARCHAR2"
    AliasName="MOBILE_COUNTRY_CODE"
    Expression="MOBILE_COUNTRY_CODE"
    SQLType="VARCHAR">
    <DesignTime>
      <Attr Name="_DisplaySize" Value="100"/>
    </DesignTime>
  </ViewAttribute>
  <ViewAttribute
    Name="MobileAreaCode"
    IsUpdateable="false"
    IsPersistent="false"
    PrecisionRule="true"
    Precision="100"
    Type="java.lang.String"
    ColumnType="VARCHAR2"
    AliasName="MOBILE_AREA_CODE"
    Expression="MOBILE_AREA_CODE"
    SQLType="VARCHAR">
    <DesignTime>
      <Attr Name="_DisplaySize" Value="100"/>
    </DesignTime>
  </ViewAttribute>
  <ViewAttribute
    Name="Mobile"
    IsUpdateable="false"
    IsPersistent="false"
    PrecisionRule="true"
    Precision="100"
    Type="java.lang.String"
    ColumnType="VARCHAR2"
    AliasName="MOBILE"
    Expression="MOBILE"
    SQLType="VARCHAR">
    <DesignTime>
      <Attr Name="_DisplaySize" Value="100"/>
    </DesignTime>
  </ViewAttribute>
  <ViewAttribute
    Name="MobileNumber"
    IsUpdateable="false"
    IsPersistent="false"
    PrecisionRule="true"
    Precision="100"
    Type="java.lang.String"
    ColumnType="VARCHAR2"
    AliasName="MOBILE_NUMBER"
    Expression="MOBILE_NUMBER"
    SQLType="VARCHAR">
    <DesignTime>
      <Attr Name="_DisplaySize" Value="100"/>
    </DesignTime>
  </ViewAttribute>
  <ViewAttribute
    Name="Status"
    IsUpdateable="false"
    IsPersistent="false"
    PrecisionRule="true"
    Precision="1"
    Type="java.lang.String"
    ColumnType="VARCHAR2"
    AliasName="STATUS"
    Expression="STATUS"
    SQLType="VARCHAR">
    <DesignTime>
      <Attr Name="_DisplaySize" Value="1"/>
    </DesignTime>
  </ViewAttribute>
  <ViewAttribute
    Name="InactiveDate"
    IsUpdateable="false"
    IsPersistent="false"
    PrecisionRule="true"
    Type="oracle.jbo.domain.Date"
    ColumnType="DATE"
    AliasName="INACTIVE_DATE"
    Expression="INACTIVE_DATE"
    SQLType="DATE">
    <DesignTime>
      <Attr Name="_DisplaySize" Value="7"/>
    </DesignTime>
  </ViewAttribute>
  <ViewCriteria
    Name="findBySiteID_Con_ID"
    ViewObjectName="ROVO.supplierContactROVO"
    Conjunction="AND">
    <Properties>
      <CustomProperties>
        <Property
          Name="displayOperators"
          Value="InAdvancedMode"/>
        <Property
          Name="autoExecute"
          Value="false"/>
        <Property
          Name="allowConjunctionOverride"
          Value="true"/>
        <Property
          Name="showInList"
          Value="true"/>
        <Property
          Name="mode"
          Value="Basic"/>
      </CustomProperties>
    </Properties>
    <ViewCriteriaRow
      Name="vcrow189"
      UpperColumns="1">
      <ViewCriteriaItem
        Name="VendorContactId"
        ViewAttribute="VendorContactId"
        Operator="="
        Conjunction="AND"
        Value=":BV_CONT_ID"
        IsBindVarValue="true"
        Required="Optional"/>
      <ViewCriteriaItem
        Name="VendorSiteId"
        ViewAttribute="VendorSiteId"
        Operator="="
        Conjunction="AND"
        Value=":BV_Site_ID"
        IsBindVarValue="true"
        Required="Optional"/>
    </ViewCriteriaRow>
  </ViewCriteria>
  <AttrArray Name="KeyAttributes">
    <Item Value="VendorContactId"/>
  </AttrArray>
  <ResourceBundle>
    <PropertiesBundle
      PropertiesFile="subcontract.model.SubContractModelBundle"/>
  </ResourceBundle>
</ViewObject>
